porunga/__init__.py
porunga/procme.py
porunga/commands/__init__.py
porunga/commands/test.py
porunga/tests/__init__.py
porunga/tests/test_commands_test.py
porunga/tests/test_main.py
porunga/tests/test_utils_backports.py
porunga/utils/__init__.py
porunga/utils/backports.py
porunga/utils/compat.py
porunga/utils/imports.py
porunga/utils/paths.py
porunga/utils/shell.py
porunga-0.9.3.data/scripts/porunga
porunga-0.9.3.dist-info/DESCRIPTION.rst
porunga-0.9.3.dist-info/entry_points.txt
porunga-0.9.3.dist-info/METADATA
porunga-0.9.3.dist-info/pydist.json
porunga-0.9.3.dist-info/RECORD
porunga-0.9.3.dist-info/top_level.txt
porunga-0.9.3.dist-info/WHEEL
porunga.egg-info/dependency_links.txt
porunga.egg-info/entry_points.txt
porunga.egg-info/not-zip-safe
porunga.egg-info/PKG-INFO
porunga.egg-info/requires.txt
porunga.egg-info/SOURCES.txt
porunga.egg-info/top_level.txt
