Metadata-Version: 2.0
Name: porunga
Version: 0.9.3
Summary: 
Requires-Dist: monolith
Requires-Dist: termcolor
